git_ignore/__init__.py
git_ignore/__version__.py
git_ignore/main.py
git_ignore/template/Actionscript.gitignore
git_ignore/template/Ada.gitignore
git_ignore/template/Agda.gitignore
git_ignore/template/Android.gitignore
git_ignore/template/AppEngine.gitignore
git_ignore/template/AppceleratorTitanium.gitignore
git_ignore/template/ArchLinuxPackages.gitignore
git_ignore/template/Autotools.gitignore
git_ignore/template/C++.gitignore
git_ignore/template/C.gitignore
git_ignore/template/CFWheels.gitignore
git_ignore/template/CMake.gitignore
git_ignore/template/CUDA.gitignore
git_ignore/template/CakePHP.gitignore
git_ignore/template/ChefCookbook.gitignore
git_ignore/template/Clojure.gitignore
git_ignore/template/CodeIgniter.gitignore
git_ignore/template/CommonLisp.gitignore
git_ignore/template/Composer.gitignore
git_ignore/template/Concrete5.gitignore
git_ignore/template/Coq.gitignore
git_ignore/template/CraftCMS.gitignore
git_ignore/template/D.gitignore
git_ignore/template/DM.gitignore
git_ignore/template/Dart.gitignore
git_ignore/template/Delphi.gitignore
git_ignore/template/Drupal.gitignore
git_ignore/template/EPiServer.gitignore
git_ignore/template/Eagle.gitignore
git_ignore/template/Elisp.gitignore
git_ignore/template/Elixir.gitignore
git_ignore/template/Elm.gitignore
git_ignore/template/Erlang.gitignore
git_ignore/template/ExpressionEngine.gitignore
git_ignore/template/ExtJs.gitignore
git_ignore/template/Fancy.gitignore
git_ignore/template/Finale.gitignore
git_ignore/template/ForceDotCom.gitignore
git_ignore/template/Fortran.gitignore
git_ignore/template/FuelPHP.gitignore
git_ignore/template/GWT.gitignore
git_ignore/template/Gcov.gitignore
git_ignore/template/GitBook.gitignore
git_ignore/template/Go.gitignore
git_ignore/template/Godot.gitignore
git_ignore/template/Gradle.gitignore
git_ignore/template/Grails.gitignore
git_ignore/template/Haskell.gitignore
git_ignore/template/IGORPro.gitignore
git_ignore/template/Idris.gitignore
git_ignore/template/JBoss.gitignore
git_ignore-1.0.2.dist-info/LICENSE
git_ignore-1.0.2.dist-info/METADATA
git_ignore-1.0.2.dist-info/WHEEL
git_ignore-1.0.2.dist-info/entry_points.txt
git_ignore-1.0.2.dist-info/top_level.txt
git_ignore-1.0.2.dist-info/zip-safe
git_ignore-1.0.2.dist-info/RECORD
