Metadata-Version: 2.1
Name: git-ignore
Version: 1.0.2
Summary: .gitignore Template Generator
Home-page: https://github.com/hanpannet/Git-ignore
Author: Qiushi Pan
Author-email: ice.gitshell@gmail.com
License: MIT
Keywords: git gitignore file template default
Platform: UNKNOWN
Classifier: Environment :: Console
Classifier: Intended Audience :: Developers
Classifier: Operating System :: MacOS :: MacOS X
Classifier: Programming Language :: Python :: 3
Classifier: Programming Language :: Python :: 3.3
Classifier: Programming Language :: Python :: 3.4
Classifier: Programming Language :: Python :: 3.5
Classifier: Programming Language :: Python :: 3.6
Classifier: Programming Language :: Python :: 3.7
